LICENSE
MANIFEST.in
README.md
requirements.txt
setup.py
byteplus/__init__.py
byteplus/__version__.py
byteplus.egg-info/PKG-INFO
byteplus.egg-info/SOURCES.txt
byteplus.egg-info/dependency_links.txt
byteplus.egg-info/requires.txt
byteplus.egg-info/top_level.txt
byteplus/common/__init__.py
byteplus/common/client.py
byteplus/common/url.py
byteplus/common/protocol/__init__.py
byteplus/common/protocol/byteplus_common_pb2.py
byteplus/core/__init__.py
byteplus/core/constant.py
byteplus/core/context.py
byteplus/core/exception.py
byteplus/core/host_availabler.py
byteplus/core/host_availabler_config.py
byteplus/core/http_caller.py
byteplus/core/option.py
byteplus/core/options.py
byteplus/core/region.py
byteplus/core/url_center.py
byteplus/core/utils.py
byteplus/core/metrics/__init__.py
byteplus/core/metrics/constant.py
byteplus/core/metrics/metrics.py
byteplus/core/metrics/metrics_collector.py
byteplus/core/metrics/metrics_example.py
byteplus/core/metrics/metrics_log.py
byteplus/core/metrics/metrics_option.py
byteplus/core/metrics/metrics_reporter.py
byteplus/core/metrics/protocol/__init__.py
byteplus/core/metrics/protocol/byteplus_sdk_metrics_pb2.py
byteplus/general/__init__.py
byteplus/general/client.py
byteplus/general/url.py
byteplus/general/protocol/__init__.py
byteplus/general/protocol/byteplus_general_pb2.py
byteplus/media/__init__.py
byteplus/media/client.py
byteplus/media/url.py
byteplus/media/protocol/__init__.py
byteplus/media/protocol/byteplus_media_pb2.py
byteplus/retail/__init__.py
byteplus/retail/client.py
byteplus/retail/url.py
byteplus/retail/protocol/__init__.py
byteplus/retail/protocol/byteplus_retail_pb2.py
byteplus/retailv2/__init__.py
byteplus/retailv2/client.py
byteplus/retailv2/url.py
byteplus/retailv2/protocol/__init__.py
byteplus/retailv2/protocol/byteplus_retailv2_pb2.py
byteplus/rutenad/__init__.py
byteplus/rutenad/client.py
byteplus/rutenad/url.py
byteplus/rutenad/protocol/__init__.py
byteplus/rutenad/protocol/byteplus_ruten_ad_pb2.py
byteplus/volcauth/__init__.py
byteplus/volcauth/exceptions.py
byteplus/volcauth/volcauth.py
byteplus/volcauth/volcsigningkey.py